
     [
      {
        "id": 1,
        "name": "Spaghetti Carbonara",
        "ctg_id":2,
        "details": "A classic Italian dish made with spaghetti, eggs, bacon, and cheese.",
        "elements": [
          "1 pound spaghetti",
          "6 ounces bacon, diced",
          "4 large eggs",
          "1 cup grated Parmesan cheese",
          "Salt and freshly ground black pepper"
        ],
        "rating":3.5,
        "image": "https://img.freepik.com/free-photo/stir-fried-spaghetti-beautifully-arranged-white-plate_1150-22143.jpg?w=996&t=st=1683110123~exp=1683110723~hmac=6ca64aa85e1be9750486f117799fdc63c8440c84795a3586a29cdf72fe30ebb3"
      },
      {
        "id": 2,
        "ctg_id":1,
        "name": "Margherita Pizza",
        "details": "A simple but delicious pizza made with tomato sauce, mozzarella cheese, and fresh basil.",
        "elements": [
          "1 pound pizza dough",
          "1/2 cup tomato sauce",
          "8 ounces fresh mozzarella cheese, sliced",
          "1/4 cup fresh basil leaves",
          "Salt and freshly ground black pepper"
        ],
        "rating":4,
        "image": "https://img.freepik.com/free-photo/tasty-homemade-traditional-pizza-italian-recipe_24972-2141.jpg?w=996&t=st=1683110065~exp=1683110665~hmac=4ef30aa9224d54cd35c2c833bd98a63b40c3042d05b3259f57dd68dcd4d66031"
      },
      {
        "id": 3,
        "ctg_id":3,
        "name": "Chicken Parmesan",
        "details": "A classic Italian-American dish made with breaded chicken, tomato sauce, and melted cheese.",
        "elements": [
          "4 boneless, skinless chicken breasts",
          "1/2 cup all-purpose flour",
          "2 large eggs, beaten",
          "1 cup Italian-style breadcrumbs",
          "1 cup tomato sauce",
          "1 cup shredded mozzarella cheese",
          "1/4 cup grated Parmesan cheese",
          "Salt and freshly ground black pepper"
        ],
        "rating":5,
        "image": "https://img.freepik.com/free-photo/rice-garnish-with-herbs-chicken-breast-iron-plate_114579-1955.jpg?w=996&t=st=1683110020~exp=1683110620~hmac=283c7976a7ced32bed3663c81975924181690eb7fd454be63e9da1a88f109faf"
      },
      {
        "id": 4,
        "ctg_id":4,
        "name": "Lasagna",
        "details": "A classic Italian dish made with layers of pasta, meat sauce, and cheese.",
        "elements": [
          "1 pound ground beef",
          "1/2 pound Italian sausage",
          "1 jar (24 ounces) spaghetti sauce",
          "1 can (14.5 ounces) diced tomatoes",
          "1 teaspoon dried basil",
          "1 teaspoon dried oregano",
          "1/2 teaspoon salt",
          "1/4 teaspoon black pepper",
          "8 lasagna noodles, cooked and drained",
          "2 cups shredded mozzarella cheese",
          "1/2 cup grated Parmesan cheese"
        ],
        "rating":3,
        "image": "https://img.freepik.com/free-photo/high-angle-view-tablecloth-fresh-ingredient-delicious-lasagna_23-2148076281.jpg?w=996&t=st=1683109965~exp=1683110565~hmac=14774606fbabacf50a68770cb8914118c991e0898b628d316d6b281af88e302c"
      },
      {
        "id": 5,
        "ctg_id":5,
        "name": "Fettuccine Alfredo",
        "details": "A creamy pasta dish made with fettuccine noodles and a sauce made from butter, cream, and Parmesan cheese.",
        "elements": [
          "1 pound fettuccine pasta",
          "1/2 cup unsalted butter",
          "2 cups heavy cream",
          "2 cups grated Parmesan cheese",
          "1/2 teaspoon salt",
          "1/4 teaspoon black pepper"
        ],
        "rating":3,
        "image": "https://img.freepik.com/free-photo/pasta-cream-sauce-with-chicken-parmesan_140725-2173.jpg?w=740&t=st=1683109913~exp=1683110513~hmac=5c88f6bc7639f6451173831fe05e4068490da018402c23085c2b2ec986e273cb"
      },
      {
        "id": 6,
        "ctg_id":6,
        "name": "Caprese Salad",
        "details": "A refreshing salad made with fresh mozzarella cheese, ripe tomatoes, and fresh basil.",
        "elements": [
          "1 pound fresh mozzarella cheese, sliced",
          "3 large tomatoes, sliced",
          "1/4 cup fresh basil leaves",
          "2 tablespoons balsamic vinegar",
          "2 tablespoons olive oil",
          "Salt and freshly ground black pepper"
        ],
        "rating":4.5,
        "image": "https://img.freepik.com/free-photo/italian-caprese-salad-with-tomatoes-basil-mozzarella-olives-olive-oil-wooden-board-italian-traditional-caprese-salad-ingredients-mediterranean-organic-natural-food-concept_1150-44847.jpg?w=996&t=st=1683109868~exp=1683110468~hmac=ad78645ff51d14d6c82bee5510fc0f74d5aef56074e0d7c0c7b0f54f4aadf411"
      },
      {
        "id": 7,
        "ctg_id":1,
        "name": "Pesto Pasta",
        "details": "A flavorful pasta dish made with basil pesto, pine nuts, and Parmesan cheese.",
        "elements": [
          "1 pound linguine pasta",
          "2 cups fresh basil leaves",
          "1/2 cup pine nuts",
          "1/2 cup grated Parmesan cheese",
          "1/2 cup olive oil",
          "3 cloves garlic",
          "Salt and freshly ground black pepper"
        ],
        "rating":3.5,
        "image": "https://img.freepik.com/free-photo/penne-pasta-with-pesto-sauce-zucchini-green-peas-basil-italian-food_2829-5833.jpg?w=996&t=st=1683109793~exp=1683110393~hmac=e11584ecc3f609b4d680fe8bbe64dc06d6e7bc5e28dedb09bfb007842325ea98"
      },
      {
        "id": 8,
        "ctg_id":2,
        "name": "Minestrone Soup",
        "details": "A hearty soup made with vegetables, beans, and pasta.",
        "elements": [
          "2 tablespoons olive oil",
          "1 onion, chopped",
          "3 cloves garlic, minced",
          "3 carrots, peeled and chopped",
          "3 celery stalks, chopped",
          "1 can (14.5 ounces) diced tomatoes",
          "4 cups vegetable broth",
          "1 can (15 ounces) cannellini beans, drained and rinsed",
          "1 cup uncooked small pasta",
          "1/4 cup chopped fresh parsley",
          "Salt and freshly ground black pepper"
        ],
        "rating":4,
        "image": "https://img.freepik.com/free-photo/delicious-tapas-food-assortment_23-2148960514.jpg?w=360&t=st=1683110238~exp=1683110838~hmac=685baf51c571b24feb2a6b3d81e273ba3776a76a7403bcc4d4f3341fa93513cc"
      },
      {
        "id": 9,
        "ctg_id":3,
        "name": "Tiramisu",
        "details": "A classic Italian dessert made with ladyfingers, espresso, and a creamy mascarpone cheese filling.",
        "elements": [
          "1 cup heavy cream",
          "8 ounces mascarpone cheese",
          "1/4 cup sugar",
          "1/4 cup brewed espresso, cooled",
          "24 ladyfingers",
          "2 tablespoons unsweetened cocoa powder"
        ],
        "rating":5,
        "image": "https://img.freepik.com/free-photo/tasty-homemade-tiramisu-cake_114579-85350.jpg?w=996&t=st=1683109741~exp=1683110341~hmac=9045f8e88b898d43674a3738729bdc78a951987c32cc8cadaef049dc2f849a68"
      },
      {
        "id": 10,
        "ctg_id":4,
        "name": "Osso Buco",
        "details": "A flavorful dish made with veal shanks braised in white wine and vegetables.",
        "elements": [
          "4 veal shanks",
          "1/2 cup all-purpose flour",
          "2 tablespoons olive oil",
          "1 onion, chopped",
          "3 carrots, peeled and chopped",
          "3 celery stalks, chopped",
          "1 cup white wine",
          "1 can (14.5 ounces) diced tomatoes",
          "2 cups beef broth",
          "3 cloves garlic, minced",
          "1 teaspoon dried thyme",
          "Salt and freshly ground black pepper"
        ],
        "rating":4.5,
        "image": "https://img.freepik.com/free-photo/roasted-grilled-beef-liver-with-onion-tomatoes-salad_2829-10730.jpg?w=996&t=st=1683109695~exp=1683110295~hmac=252c536e3ab4418ff8781f4b8d89865daab8ddd8e21fba3e4375f8bc0a9ec80b"
      },  {
        "id": 11,
        "ctg_id":5,
        "name": "Chicken Parmesan",
        "details": "A classic Italian-American dish made with breaded chicken breasts, tomato sauce, and mozzarella cheese.",
        "elements": [
          "4 boneless, skinless chicken breasts",
          "1/2 cup all-purpose flour",
          "2 large eggs, beaten",
          "1 cup Italian-seasoned breadcrumbs",
          "1/2 cup grated Parmesan cheese",
          "2 cups tomato sauce",
          "2 cups shredded mozzarella cheese",
          "2 tablespoons olive oil",
          "Salt and freshly ground black pepper"
        ],
        "rating":5,
        "image": "https://img.freepik.com/free-photo/delicious-rice-chicken-meat-patties-with-garlic-tomato-sauce_2829-11011.jpg?w=996&t=st=1683109647~exp=1683110247~hmac=e3bb230d09925a0ee4892f08931639d7389c5fd553352324ba45d8ed0dd3854e"
      },
      {
        "id": 12,
        "ctg_id":6,
        "name": "Spaghetti Carbonara",
        "details": "A simple pasta dish made with spaghetti, eggs, bacon, and Parmesan cheese.",
        "elements": [
          "1 pound spaghetti",
          "8 ounces bacon, diced",
          "4 large eggs",
          "1 cup grated Parmesan cheese",
          "Salt and freshly ground black pepper"
        ],
        "rating":4.5,
        "image": "https://img.freepik.com/free-photo/top-view-tasty-italian-pasta-white-background_140725-136591.jpg?w=996&t=st=1683109568~exp=1683110168~hmac=2781d60f412d24d56c4b3fa4c00c39fe61224b100c11b3c262529c246660ae27"
      },
      {
        "id": 13,
        "ctg_id":1,
        "name": "Risotto",
        "details": "A creamy rice dish made with Arborio rice, white wine, and Parmesan cheese.",
        "elements": [
          "1 onion, chopped",
          "2 tablespoons olive oil",
          "1 1/2 cups Arborio rice",
          "1/2 cup white wine",
          "4 cups chicken broth",
          "1/2 cup grated Parmesan cheese",
          "2 tablespoons butter",
          "Salt and freshly ground black pepper"
        ],
        "rating":3,
        "image": "https://img.freepik.com/free-photo/pasta-with-broccoli-dried-tomatoes_661915-501.jpg?w=996&t=st=1683109507~exp=1683110107~hmac=ee4453079e9f0fdd5ee2623a543cc6565a63de5f649ef5cb655d89f317c7775c"
      },
      {
        "id": 14,
        "ctg_id":2,
        "name": "Lasagna",
        "details": "A layered pasta dish made with ground beef, tomato sauce, and ricotta and mozzarella cheese.",
        "elements": [
          "12 lasagna noodles",
          "1 pound ground beef",
          "1 jar (24 ounces) tomato sauce",
          "1/2 cup water",
          "2 cups ricotta cheese",
          "2 cups shredded mozzarella cheese",
          "1/2 cup grated Parmesan cheese",
          "2 tablespoons olive oil",
          "Salt and freshly ground black pepper"
        ],
        "rating":4,
        "image": "https://img.freepik.com/free-photo/classic-lasagna-with-bolognese-sauce_2829-11237.jpg?w=996&t=st=1683109446~exp=1683110046~hmac=693e3e224b5a04457f19dea737a95d111378fd4a0e039e0b73c35975aea96184"
      },
      {
        "id": 15,
        "ctg_id":3,
        "name": "Bruschetta",
        "details": "A simple Italian appetizer made with toasted bread, tomatoes, and basil.",
        "elements": [
          "1 loaf Italian bread, sliced",
          "3 large tomatoes, chopped",
          "2 cloves garlic, minced",
          "1/4 cup chopped fresh basil",
          "1/4 cup olive oil",
          "Salt and freshly ground black pepper"
        ],
        "rating":4,
        "image": "https://img.freepik.com/free-photo/tasty-bruschetta-with-tomatoes-basil_1220-7128.jpg?w=996&t=st=1683109400~exp=1683110000~hmac=676086baddf2cb7d7b2e35311fe454bf1f3dac6b813fec66a713f6d13fb6898b"
      }, {
        "id": 16,
        "ctg_id":3,
        "name": "Chicken Parmesan",
        "details": "A classic Italian-American dish made with breaded chicken breasts, tomato sauce, and mozzarella cheese.",
        "elements": [
          "4 boneless, skinless chicken breasts",
          "1/2 cup all-purpose flour",
          "2 large eggs, beaten",
          "1 cup Italian-seasoned breadcrumbs",
          "1/2 cup grated Parmesan cheese",
          "2 cups tomato sauce",
          "2 cups shredded mozzarella cheese",
          "2 tablespoons olive oil",
          "Salt and freshly ground black pepper"
        ],
        "rating":4.5,
        "image": "https://img.freepik.com/free-photo/vegetarian-vegetable-casserole-with-zucchini-mushrooms-cherry-tomatoes_2829-11069.jpg?w=996&t=st=1683109345~exp=1683109945~hmac=d5d8dddcae0eac052cedd49da9c3deb12663a099ca189e3ce9314db242849e4f"
      },
      {
        "id": 17,
        "ctg_id":4,
        "name": "Spaghetti Carbonara",
        "details": "A simple pasta dish made with spaghetti, eggs, bacon, and Parmesan cheese.",
        "elements": [
          "1 pound spaghetti",
          "8 ounces bacon, diced",
          "4 large eggs",
          "1 cup grated Parmesan cheese",
          "Salt and freshly ground black pepper"
        ],
        "rating":3.5,
        "image": "https://img.freepik.com/free-photo/spaghetti-with-mixed-ingredients-white-plate_114579-15091.jpg?w=996&t=st=1683109288~exp=1683109888~hmac=339bc50542e4292ed1e2507d1da56fcb83474791e1bf1b45a1f7c95b571b1fa5"
      },
      {
        "id": 18,
        "name": "Risotto",
        "ctg_id":5,
        "details": "A creamy rice dish made with Arborio rice, white wine, and Parmesan cheese.",
        "elements": [
          "1 onion, chopped",
          "2 tablespoons olive oil",
          "1 1/2 cups Arborio rice",
          "1/2 cup white wine",
          "4 cups chicken broth",
          "1/2 cup grated Parmesan cheese",
          "2 tablespoons butter",
          "Salt and freshly ground black pepper"
        ],
        "rating":5,
        "image": "https://img.freepik.com/free-photo/plate-mushroom-risotto-topped-with-grated-cheese_141793-469.jpg?w=740&t=st=1683109241~exp=1683109841~hmac=497555b61309e0bde492c76fb3edf07d2c7e92a7fed5cd302441475bca0d3c79"
      },
      {
        "id": 19,
        "ctg_id":6,
        "name": "Lasagna",
        "details": "A layered pasta dish made with ground beef, tomato sauce, and ricotta and mozzarella cheese.",
        "elements": [
          "12 lasagna noodles",
          "1 pound ground beef",
          "1 jar (24 ounces) tomato sauce",
          "1/2 cup water",
          "2 cups ricotta cheese",
          "2 cups shredded mozzarella cheese",
          "1/2 cup grated Parmesan cheese",
          "2 tablespoons olive oil",
          "Salt and freshly ground black pepper"
        ],
        "rating":3.4,
        "image": "https://img.freepik.com/free-photo/classic-lasagna-with-bolognese-sauce_2829-14066.jpg?w=740&t=st=1683109189~exp=1683109789~hmac=a19326b5eb120170d350bd143fae74502188e494d5fd6a904d3d328b0c424389"
      },
      {
        "id": 20,
        "ctg_id":1,
        "name": "Bruschetta",
        "details": "A simple Italian appetizer made with toasted bread, tomatoes, and basil.",
        "elements": [
          "1 loaf Italian bread, sliced",
          "3 large tomatoes, chopped",
          "2 cloves garlic, minced",
          "1/4 cup chopped fresh basil",
          "1/4 cup olive oil",
          "Salt and freshly ground black pepper"
        ],
        "rating":3,
        "image": "https://img.freepik.com/free-photo/bruschetta-chopping-board_144627-17674.jpg?w=996&t=st=1683109136~exp=1683109736~hmac=39267fb1b826421614c9b7dea476d3a6c7bfd9fc27f48e0e958c930371063f93"
      }
    ]
  